studysmarter/Response.py
studysmarter/StudySmarterAccount.py
studysmarter/StudySmarterStudySets.py
studysmarter/__init__.py
studysmarter/endpoints.py
studysmarter/errors.py
studysmarter/login.py
studysmarter/utils.py
studysmarter-0.0.2.dist-info/LICENSE
studysmarter-0.0.2.dist-info/METADATA
studysmarter-0.0.2.dist-info/WHEEL
studysmarter-0.0.2.dist-info/top_level.txt
studysmarter-0.0.2.dist-info/RECORD
