Metadata-Version: 2.1
Name: studysmarter
Version: 0.0.2
Summary: An API Wrapper for StudySmarter
Author: Issac
Keywords: python,web surface,web scrape,http request,requests,studysmarter,anki,wrapper
Classifier: Development Status :: 1 - Planning
Classifier: Intended Audience :: Developers
Classifier: Programming Language :: Python :: 3
Classifier: Operating System :: Unix
Classifier: Operating System :: MacOS :: MacOS X
Classifier: Operating System :: Microsoft :: Windows
License-File: LICENSE
